{"transcript":"freˈɡate","exists":true,"definitions":["Nave da guerra veloce e maneggevole, di dimensioni medie, usata per scorta e pattugliamento.","Uccello marino tropicale della famiglia Fregatidae, noto per le sue lunghe ali e la coda biforcuta."],"examples":["La fregate salpò all'alba.","Le fregate volavano sopra l'isola."],"lemma":"fregata","lemmaPos":"noun","synonyms":["corvetta","veliero","uccello fregata"],"number":"plural","pluralForm":"le fregate","gender":"feminine","source":"fregate"}