{"transcript":"at.tak.ˈka.re","exists":true,"definitions":["Unire o congiungere una cosa a un'altra.","Compiere un'azione offensiva contro qualcuno o qualcosa.","Iniziare a fare qualcosa, specialmente parlare o suonare.","Trasmettere una malattia per contagio."],"examples":["Attaccare un bottone.","Attaccare il nemico.","Attaccare discorso.","Attaccare l'influenza."],"lemma":"attaccare","lemmaPos":"verb","synonyms":["appendere","assalire","incollare","iniziare","contagiare"],"number":"singular","pastTenses":"attaccai, ho attaccato","tense":"present","source":"attaccare"}