{"transcript":"korˈrɛdo","exists":true,"definitions":["Insieme di abiti, biancheria e oggetti necessari a una persona per una particolare circostanza.","Complesso di strumenti o dotazioni che completano un apparato o un servizio.","Insieme di nozioni o doti intellettuali e morali di una persona."],"examples":["Il corredo nuziale.","Un ricco corredo di illustrazioni.","Il corredo cromosomico."],"lemma":"corredo","lemmaPos":"noun","synonyms":["dotazione","equipaggiamento","bagaglio","armamentario"],"number":"singular","pluralForm":"i corredi","gender":"masculine","source":"corredo"}