{"transcript":"zviˈluppo","exists":true,"definitions":["Azione di sviluppare, di far crescere o progredire qualcosa.","Il processo di crescita o evoluzione di un organismo, un'idea, un progetto.","La fase di elaborazione e realizzazione di un prodotto o servizio."],"examples":["Lo sviluppo economico del paese è fondamentale.","Il progetto è ancora in fase di sviluppo.","Lo sviluppo di nuove tecnologie è rapido."],"lemma":"sviluppare","lemmaPos":"verb","synonyms":["crescita","progresso","evoluzione","espansione"],"number":"singular","pastTenses":"ho sviluppato, ho sviluppato","tense":"present","gender":"masculine","source":"sviluppo"}