{"transcript":"barriˈkate","exists":true,"definitions":["Seconda persona plurale dell'indicativo presente di barricare.","Seconda persona plurale dell'imperativo presente di barricare.","Participio passato femminile plurale di barricare."],"examples":["Voi barricate la porta.","Barricate le entrate subito!","Le strade sono barricate."],"lemma":"barricare","lemmaPos":"verb","synonyms":["sbarrare","ostruire","chiudere","blindare"],"number":"plural","pastTenses":"barricai, avete barricato, sono state barricate","tense":"present","gender":"feminine","source":"barricate"}