{"transcript":"ˈfwo.ri","exists":true,"definitions":["All'esterno, all'aperto.","Al di fuori di un luogo o di un contenitore.","In posizione esterna rispetto a qualcosa.","Lontano da un luogo, via.","Escluso, non incluso.","In stato di incoscienza o fuori controllo."],"examples":["È fuori casa.","Metti i libri fuori.","Il gatto è fuori dalla finestra.","Andiamo fuori a cena.","Sei fuori dal gioco.","È fuori di sé dalla rabbia."],"lemma":"fuori","lemmaPos":"adverb","synonyms":["all'esterno","all'aperto","esteriormente"],"number":"singular","source":"fuori"}