{"source":"rivoluzioni","number":"plural","lemma":"rivoluzione","lemmaPos":"noun","definitions":["Cambiamento radicale e spesso violento dell'ordinamento politico e sociale di uno stato.","Cambiamento profondo e spesso rapido in un campo specifico (es. scientifico, industriale).","Movimento di un corpo celeste intorno a un altro o intorno al proprio asse."],"examples":["Le rivoluzioni del XVIII secolo hanno plasmato l'Europa.","La rivoluzione industriale ha trasformato la società.","Le rivoluzioni planetarie sono calcolate con precisione."],"synonyms":["cambiamenti","sommosse","rivolte","mutamenti"],"transcript":"rivoluzioni","gender":"feminine","pluralForm":"le rivoluzioni"}