{"transcript":"as.senˈta.re","exists":true,"definitions":["Allontanare, mandare via.","Rendere assente, far mancare.","Riflessivo: allontanarsi, mancare dal proprio posto o dovere."],"examples":["Il preside decise di assentare lo studente per una settimana.","Si assentò dalla riunione senza preavviso.","Non assentare mai la tua mente dai tuoi obiettivi."],"lemma":"assentare","lemmaPos":"verb","synonyms":["allontanare","mancare","defalcare"],"number":"singular","tense":"present","pastTenses":"assentò (past simple), ha assentato (present perfect)","source":"assentare"}