{"transcript":"ˈskat.to","exists":true,"definitions":["Movimento rapido e improvviso.","Aumento improvviso e significativo (di prezzo, velocità, ecc.).","Fotografia, immagine catturata.","Scatto di un'arma da fuoco."],"examples":["Ha avuto uno scatto d'ira.","Il prezzo ha fatto uno scatto verso l'alto.","Ho visto il suo scatto sulla rivista.","Lo scatto del fucile ha spaventato tutti."],"lemma":"scatto","lemmaPos":"noun","synonyms":["balzo","salto","fotografia","aumento"],"number":"singular","pluralForm":"gli scatti","gender":"masculine","source":"scatto"}