{"transcript":"konferˈmare","exists":true,"definitions":["Dare conferma di qualcosa, assicurare la veridicità o l'esistenza di un fatto.","Rendere valido o definitivo un atto, una decisione, un accordo.","Riaffermare la propria fede, un'idea, un impegno."],"examples":["Puoi confermare la prenotazione?","Il consiglio ha deciso di confermare il presidente.","Confermo la mia partecipazione all'evento."],"lemma":"confermare","lemmaPos":"verb","synonyms":["validare","ratificare","avvalorare","ribadire","assicurare"],"number":"singular","pastTenses":"ho confermato, hai confermato, ha confermato, abbiamo confermato, avete confermato, hanno confermato","tense":"present","source":"confermare"}