{"transcript":"fa","exists":true,"definitions":["Terza persona singolare dell'indicativo presente del verbo fare.","Compiere un'azione.","Creare, produrre.","Causare, provocare.","Riferito al tempo, indica un periodo trascorso."],"examples":["Lui fa i compiti ogni giorno.","Questo rumore mi fa male alla testa.","Quanto tempo fa è successo?","La nonna fa una torta deliziosa.","Il bambino fa un disegno."],"lemma":"fare","lemmaPos":"verb","synonyms":["compiere","creare","eseguire","produrre","causare"],"number":"singular","pastTenses":"fece, ha fatto","tense":"present","source":"fa"}