{"transcript":"falˈlire","exists":true,"definitions":["Non riuscire in un intento o in un'impresa.","Andare in bancarotta, dichiarare fallimento."],"examples":["Ha paura di fallire all'esame.","Molte aziende falliscono durante le crisi economiche.","Nonostante gli sforzi, il progetto è fallito."],"lemma":"fallire","lemmaPos":"verb","synonyms":["mancare","sbagliare","naufragare","bancarotta"],"number":"singular","tense":"present","pastTenses":"fallì (past simple), è fallito (present perfect)","source":"fallire"}