{"transcript":"inˈkrot.t͡ʃo","exists":true,"definitions":["Punto in cui due o più strade si tagliano a vicenda.","Atto di incrociare o sovrapporre due elementi.","Ibridazione tra individui di razze o specie diverse."],"examples":["Svolta a destra all'incrocio.","Un incrocio tra un leone e una tigre.","L'incrocio delle braccia."],"lemma":"incrocio","lemmaPos":"noun","synonyms":["intersezione","quadrivio","ibrido","commistione"],"number":"singular","pluralForm":"gli incroci","gender":"masculine","source":"incrocio"}