{"transcript":"ɡranˈduki","exists":true,"definitions":["Plurale di granduca, titolo nobiliare di sovrani di alcuni stati europei.","Membri di una famiglia regnante con il titolo di granduca."],"examples":["I granduchi di Toscana erano potenti.","La storia dei granduchi è affascinante.","Molti granduchi hanno lasciato un'eredità culturale."],"lemma":"granduca","lemmaPos":"noun","synonyms":["sovrani","principi","reggenti"],"number":"plural","pluralForm":"i granduchi","gender":"masculine","source":"granduchi"}