{"transcript":"istiˈtuto","exists":true,"definitions":["Ente o organismo costituito per fini scientifici, culturali, assistenziali o amministrativi.","Scuola di istruzione secondaria o superiore.","Complesso di norme che regolano un determinato settore giuridico o sociale."],"examples":["Istituto tecnico commerciale.","L'istituto della famiglia.","Lavora in un istituto di ricerca."],"lemma":"istituto","lemmaPos":"noun","synonyms":["ente","organismo","fondazione","scuola","accademia"],"number":"singular","pluralForm":"gli istituti","gender":"masculine","source":"istituto"}