{"transcript":"neˈɡare","exists":true,"definitions":["Affermare che qualcosa non è vero o non esiste.","Rifiutare di concedere o dare qualcosa.","Rinunciare a qualcosa o a qualcuno."],"examples":["Lui nega ogni accusa.","Ha negato il permesso di uscire.","Non puoi negare l'evidenza.","Si è negato al mondo per un periodo."],"lemma":"negare","lemmaPos":"verb","synonyms":["smentire","confutare","rifiutare","disconoscere"],"number":"singular","tense":"present","pastTenses":"ha negato, aveva negato","source":"negare"}