{"source":"scaletta","number":"singular","lemma":"scaletta","lemmaPos":"noun","definitions":["Piccola scala, spec. portatile o di servizio.","Successione ordinata di interventi, argomenti, numeri in uno spettacolo, una trasmissione, una riunione e sim.; programma di massima.","Serie di gradini o pioli che permette di salire o scendere da un punto all'altro, spesso in contesti specifici come piscine, barche, o letti a castello."],"examples":["La scaletta della piscina è rotta.","Abbiamo preparato una scaletta per la riunione.","Il presentatore ha seguito la scaletta dello show."],"synonyms":["programma","ordine del giorno","scala a pioli"],"transcript":"skaˈletta","gender":"feminine"}