{"transcript":"riˈkorrere","exists":true,"definitions":["Fare ricorso a qualcosa o qualcuno per aiuto o protezione.","Presentare un ricorso legale o amministrativo.","Verificarsi di nuovo, ripetersi (riferito a eventi, date)."],"examples":["Dovremo ricorrere a misure estreme.","Ha deciso di ricorrere in appello.","Il suo compleanno ricorre a dicembre."],"lemma":"ricorrere","lemmaPos":"verb","synonyms":["appellarsi","fare appello","ripetersi","avvalersi"],"number":"singular","tense":"present","pastTenses":"ricorsi (past simple), sono ricorso/a (present perfect)","source":"ricorrere"}