{"transcript":"sta.d͡ʒoˈna.re","exists":true,"definitions":["Rendere stagionato, far maturare un prodotto alimentare o un materiale.","Invecchiare, maturare (riferito a vino, formaggio, legno, ecc.).","Esporre all'aria e alle intemperie per far perdere umidità e acquisire resistenza."],"examples":["Dobbiamo stagionare il formaggio per almeno sei mesi.","Il legno è stato stagionato all'aperto per anni.","Il vino stagiona in botti di rovere."],"lemma":"stagionare","lemmaPos":"verb","synonyms":["maturare","invecchiare","essiccare"],"number":"singular","pastTenses":"ho stagionato, hai stagionato, ha stagionato, abbiamo stagionato, avete stagionato, hanno stagionato","tense":"present","source":"stagionare"}