{"transcript":"fiˈni.re","exists":true,"definitions":["Terminare, portare a compimento qualcosa.","Giungere al termine, cessare di esistere o di accadere.","Concludere un'attività o un periodo.","Capitare, trovarsi in una determinata situazione o luogo."],"examples":["Devo finire il lavoro entro stasera.","Il film finisce tra dieci minuti.","Siamo finiti in un vicolo cieco.","Ha finito di mangiare e si è alzato."],"lemma":"finire","lemmaPos":"verb","synonyms":["terminare","concludere","cessare","completare"],"number":"singular","pastTenses":"ho finito, sono finito/a","tense":"present","source":"finire"}