{"transcript":"int͡ʃiˈzjoːne","exists":true,"definitions":["L'atto o il risultato dell'incidere una superficie.","Tecnica artistica che consiste nel creare immagini su una matrice per la stampa.","Un taglio o un'incisione praticata chirurgicamente.","Il solco o il segno lasciato da un oggetto appuntito."],"examples":["L'incisione sulla roccia era antica.","Ha studiato l'arte dell'incisione.","Il chirurgo ha praticato un'incisione precisa.","L'incisione del diamante era perfetta."],"lemma":"incisione","lemmaPos":"noun","synonyms":["intaglio","scultura","taglio","solco","stampa"],"number":"singular","pluralForm":"le incisioni","gender":"feminine","source":"incisione"}