{"transcript":"interessaˈmento","exists":true,"definitions":["Atto o effetto dell'interessarsi a qualcosa o qualcuno.","Sentimento di partecipazione, di attenzione, di sollecitudine.","L'azione di mostrare interesse o preoccupazione per qualcosa o qualcuno."],"examples":["Ha mostrato grande interessamento per il progetto.","Il suo interessamento è stato sincero.","Ringrazio per l'interessamento dimostrato."],"lemma":"interessamento","lemmaPos":"noun","synonyms":["interesse","attenzione","partecipazione","sollecitudine","coinvolgimento"],"number":"singular","pluralForm":"gli interessamenti","gender":"masculine","source":"interessamento"}