{"transcript":"ar.ti.d͡ʒaˈna.le","exists":true,"definitions":["Relativo all'artigianato o agli artigiani.","Fatto a mano o con metodi tradizionali, non industrialmente.","Tipico della produzione artigianale, spesso di alta qualità e unicità."],"examples":["Birra artigianale","Produzione artigianale","Gelato artigianale","Lavorazione artigianale","Mercato artigianale"],"lemma":"artigianale","lemmaPos":"adjective","synonyms":["manuale","fatto a mano","tradizionale","non industriale"],"number":"singular","source":"artigianale"}